{
    "RecordTitle": "Brucein A",
    "IUPACName": "methyl (1R,2S,3R,6R,8R,13S,14R,15R,16S,17S)-10,15,16-trihydroxy-9,13-dimethyl-3-(3-methylbutanoyloxy)-4,11-dioxo-5,18-dioxapentacyclo[12.5.0.01,6.02,17.08,13]nonadec-9-ene-17-carboxylate",
    "CASNo": "25514-31-2",
    "MF": "C26H34O11",
    "RecordNumber": "160006",
    "MW": "522.5g/mol",
    "Keywords": "CC1=C(C(=O)C[C@]2([C@H]1C[C@@H]3[C@]45[C@@H]2[C@H]([C@@H]([C@]([C@@H]4[C@H](C(=O)O3)OC(=O)CC(C)C)(OC5)C(=O)OC)O)O)C)O",
    "SupplyCount": 8,
    "CID": 160006,
    "titlecn": "鸦胆子素 A;"
}