{
    "RecordTitle": "(Z)-6,6,7,7,8,8,8-Heptafluoro-2,2-dimethyl-5-oxooct-3-en-3-olate;ytterbium(3+)",
    "IUPACName": "(Z)-6,6,7,7,8,8,8-heptafluoro-2,2-dimethyl-5-oxooct-3-en-3-olate;ytterbium(3+)",
    "CASNo": "18323-96-1",
    "MF": "C30H30F21O6Yb2+3",
    "RecordNumber": "137699340",
    "MW": "1231.638g/mol",
    "Keywords": "CC(/C(=C/C(=O)C(F)(F)C(F)(F)C(F)(F)F)/[O-])(C)C.CC(/C(=C/C(=O)C(F)(F)C(F)(F)C(F)(F)F)/[O-])(C)C.CC(/C(=C/C(=O)C(F)(F)C(F)(F)C(F)(F)F)/[O-])(C)C.[Yb+3].[Yb+3]",
    "SupplyCount": 8,
    "CID": 137699340
}