{
    "RecordTitle": "(1R,2R,5R,8S,9S,12S,13R,14S,15S,16R,17S,20S,21S,24S)-12,17-Dihydroxy-3,8,12,17,21,25-hexamethyl-6,23-dioxaheptacyclo[13.9.2.01,16.02,14.04,13.05,9.020,24]hexacosa-3,25-diene-7,22-dione",
    "IUPACName": "(1R,2R,5R,8S,9S,12S,13R,14S,15S,16R,17S,20S,21S,24S)-12,17-dihydroxy-3,8,12,17,21,25-hexamethyl-6,23-dioxaheptacyclo[13.9.2.01,16.02,14.04,13.05,9.020,24]hexacosa-3,25-diene-7,22-dione",
    "CASNo": "1362-42-1",
    "MF": "C30H40O6",
    "RecordNumber": "131751859",
    "MW": "496.644g/mol",
    "Keywords": "C[C@H]1[C@@H]2CC[C@]([C@@H]3[C@H]4[C@H]5C=C([C@@]6([C@H]4C(=C3[C@@H]2OC1=O)C)[C@@H]5[C@@](CC[C@@H]7[C@@H]6OC(=O)[C@H]7C)(C)O)C)(C)O",
    "SupplyCount": 6,
    "CID": 131751859,
    "titlecn": "洋艾素;"
}