{
    "RecordTitle": "Triamcinolone acetonide",
    "IUPACName": "(1S,2S,4R,8S,9S,11S,12R,13S)-12-fluoro-11-hydroxy-8-(2-hydroxyacetyl)-6,6,9,13-tetramethyl-5,7-dioxapentacyclo[10.8.0.02,9.04,8.013,18]icosa-14,17-dien-16-one",
    "CASNo": "76-25-5",
    "MF": "C24H31FO6",
    "RecordNumber": "6436",
    "MW": "434.5g/mol",
    "Keywords": "C[C@]12C[C@@H]([C@]3([C@H]([C@@H]1C[C@@H]4[C@]2(OC(O4)(C)C)C(=O)CO)CCC5=CC(=O)C=C[C@@]53C)F)O",
    "SupplyCount": 27,
    "CID": 6436,
    "titlecn": "曲安奈德;9-氟-11b,21-二羟基-16a,17-[(1-甲基亚乙基)双(氧)]-孕甾-1,4-二烯-3,20-二酮;"
}