{
    "RecordTitle": "Trisodium;[[(2S,3R,5S)-3-hydroxy-5-(5-methyl-2,4-dioxopyrimidin-1-yl)oxolan-2-yl]methoxy-oxidophosphoryl] phosphate",
    "IUPACName": "trisodium;[[(2S,3R,5S)-3-hydroxy-5-(5-methyl-2,4-dioxopyrimidin-1-yl)oxolan-2-yl]methoxy-oxidophosphoryl] phosphate",
    "CASNo": "95648-78-5",
    "MF": "C10H13N2Na3O11P2",
    "RecordNumber": "133109123",
    "MW": "468.134g/mol",
    "Keywords": "CC1=CN(C(=O)NC1=O)[C@@H]2C[C@H]([C@@H](O2)COP(=O)([O-])OP(=O)([O-])[O-])O.[Na+].[Na+].[Na+]",
    "SupplyCount": 6,
    "CID": 133109123
}