{
    "RecordTitle": "Hydron;2-[(E)-1-(4-methylphenyl)-3-pyrrolidin-1-ylprop-1-enyl]pyridine;chloride;hydrate",
    "IUPACName": "hydron;2-[(E)-1-(4-methylphenyl)-3-pyrrolidin-1-ylprop-1-enyl]pyridine;chloride;hydrate",
    "CASNo": "6138-79-0",
    "MF": "C19H25ClN2O",
    "RecordNumber": "71775310",
    "MW": "332.9g/mol",
    "Keywords": "[H+].CC1=CC=C(C=C1)/C(=C\\CN2CCCC2)/C3=CC=CC=N3.O.[Cl-]",
    "SupplyCount": 16,
    "CID": 71775310,
    "titlecn": "盐酸曲普利啶;2-(1-(4-甲基苯基)-3-(1-吡咯烷基)-1-丙烯基)吡啶盐酸盐;"
}