{
    "RecordTitle": "C.I. Direct Violet 9, disodium salt",
    "IUPACName": "disodium;7-anilino-4-hydroxy-3-[[2-methoxy-5-methyl-4-[(4-sulfonatophenyl)diazenyl]phenyl]diazenyl]naphthalene-2-sulfonate",
    "CASNo": "6227-14-1",
    "MF": "C30H23N5Na2O8S2",
    "RecordNumber": "22594",
    "MW": "691.6g/mol",
    "Keywords": "CC1=CC(=C(C=C1N=NC2=CC=C(C=C2)S(=O)(=O)[O-])OC)N=NC3=C(C=C4C=C(C=CC4=C3O)NC5=CC=CC=C5)S(=O)(=O)[O-].[Na+].[Na+]",
    "SupplyCount": 2,
    "CID": 22594,
    "titlecn": "4-羟基-3-[[2-甲氧基-5-甲基-4-[(4-磺苯基)偶氮]苯基]偶氮]-7-(苯基氨基)-2-萘磺酸二钠盐;"
}