{
    "RecordTitle": "GlcNAc-b-1,3-GalNAc-a-PNP",
    "IUPACName": "N-[2-[5-acetamido-3-hydroxy-2-(hydroxymethyl)-6-(4-nitrophenoxy)oxan-4-yl]oxy-4,5-dihydroxy-6-(hydroxymethyl)oxan-3-yl]acetamide",
    "CASNo": "125455-64-3",
    "MF": "C22H31N3O13",
    "RecordNumber": "4641266",
    "MW": "545.5g/mol",
    "Keywords": "CC(=O)NC1C(C(C(OC1OC2C(C(OC(C2O)CO)OC3=CC=C(C=C3)[N+](=O)[O-])NC(=O)C)CO)O)O",
    "SupplyCount": 14,
    "CID": 4641266,
    "titlecn": "2-乙酰氧基-3-O-(2-乙酰氧基-2-脱氧-B-D-吡喃糖苷)-2-脱氧-A-D-半乳糖苷-4-硝基苯酯;"
}