{
    "RecordTitle": "Diethyl (2S)-2-[[4-[2-(2-amino-4-oxo-3,7-dihydropyrrolo[2,3-d]pyrimidin-5-yl)ethyl]benzoyl]amino]pentanedioate;4-methylbenzenesulfonic acid",
    "IUPACName": "diethyl (2S)-2-[[4-[2-(2-amino-4-oxo-3,7-dihydropyrrolo[2,3-d]pyrimidin-5-yl)ethyl]benzoyl]amino]pentanedioate;4-methylbenzenesulfonic acid",
    "CASNo": "165049-28-5",
    "MF": "C31H37N5O9S",
    "RecordNumber": "135741210",
    "MW": "655.723g/mol",
    "Keywords": "CCOC(=O)CC[C@@H](C(=O)OCC)NC(=O)C1=CC=C(C=C1)CCC2=CNC3=C2C(=O)NC(=N3)N.CC1=CC=C(C=C1)S(=O)(=O)O",
    "SupplyCount": 5,
    "CID": 135741210
}