{
    "RecordTitle": "Nigericin",
    "IUPACName": "(2R)-2-[(2R,3S,6R)-6-[[(2S,4R,5R,6R,7R,9R)-2-[(2R,5S)-5-[(2R,3S,5R)-5-[(2S,3S,5R,6R)-6-hydroxy-6-(hydroxymethyl)-3,5-dimethyloxan-2-yl]-3-methyloxolan-2-yl]-5-methyloxolan-2-yl]-7-methoxy-2,4,6-trimethyl-1,10-dioxaspiro[4.5]decan-9-yl]methyl]-3-methyloxan-2-yl]propanoic acid",
    "CASNo": "28380-24-7",
    "MF": "C40H68O11",
    "RecordNumber": "34230",
    "MW": "725g/mol",
    "Keywords": "C[C@H]1CC[C@@H](O[C@H]1[C@@H](C)C(=O)O)C[C@@H]2C[C@H]([C@H]([C@@]3(O2)[C@@H](C[C@@](O3)(C)[C@H]4CC[C@@](O4)(C)[C@H]5[C@H](C[C@@H](O5)[C@@H]6[C@H](C[C@H]([C@@](O6)(CO)O)C)C)C)C)C)OC",
    "SupplyCount": 8,
    "CID": 34230
}