{
    "RecordTitle": "Atrasentan",
    "IUPACName": "(2R,3R,4S)-4-(1,3-benzodioxol-5-yl)-1-[2-(dibutylamino)-2-oxoethyl]-2-(4-methoxyphenyl)pyrrolidine-3-carboxylic acid",
    "CASNo": "173937-91-2",
    "MF": "C29H38N2O6",
    "RecordNumber": "159594",
    "MW": "510.6g/mol",
    "Keywords": "CCCCN(CCCC)C(=O)CN1C[C@@H]([C@H]([C@@H]1C2=CC=C(C=C2)OC)C(=O)O)C3=CC4=C(C=C3)OCO4",
    "SupplyCount": 6,
    "CID": 159594,
    "titlecn": "阿曲生坦;(2R,3R,4S)-4-(1,3-苯并二氧戊环-5-基)-1-[2-(二丁基氨基)-2-氧代乙基]-2-(4-甲氧基苯基)吡咯烷-3;"
}