{
    "RecordTitle": "[13-Ethylidene-14-[3,4,5-trihydroxy-6-(hydroxymethyl)oxan-2-yl]oxy-8,15-diazahexacyclo[14.2.1.01,9.02,7.010,15.012,17]nonadeca-2,4,6,8-tetraen-18-yl] acetate",
    "IUPACName": "[13-ethylidene-14-[3,4,5-trihydroxy-6-(hydroxymethyl)oxan-2-yl]oxy-8,15-diazahexacyclo[14.2.1.01,9.02,7.010,15.012,17]nonadeca-2,4,6,8-tetraen-18-yl] acetate",
    "CASNo": "31282-07-2",
    "MF": "C27H32N2O8",
    "RecordNumber": "639298",
    "MW": "512.6g/mol",
    "Keywords": "CC=C1C2CC3C4=NC5=CC=CC=C5C46CC(C2C6OC(=O)C)N3C1OC7C(C(C(C(O7)CO)O)O)O",
    "SupplyCount": 4,
    "CID": 639298
}