{
    "RecordTitle": "1-[(2Z)-2-(2,6-Dicarboxy-2,3-dihydro-1H-pyridin-4-ylidene)ethylidene]-6-hydroxy-5-[3,4,5-trihydroxy-6-(hydroxymethyl)oxan-2-yl]oxy-2,3-dihydroindol-1-ium-2-carboxylate",
    "IUPACName": "1-[(2Z)-2-(2,6-dicarboxy-2,3-dihydro-1H-pyridin-4-ylidene)ethylidene]-6-hydroxy-5-[3,4,5-trihydroxy-6-(hydroxymethyl)oxan-2-yl]oxy-2,3-dihydroindol-1-ium-2-carboxylate",
    "CASNo": "7659-95-2",
    "MF": "C24H26N2O13",
    "RecordNumber": "54600918",
    "MW": "550.5g/mol",
    "Keywords": "C\\1C(NC(=C/C1=C\\C=[N+]2C(CC3=CC(=C(C=C32)O)OC4C(C(C(C(O4)CO)O)O)O)C(=O)[O-])C(=O)O)C(=O)O",
    "SupplyCount": 11,
    "CID": 54600918
}