{
    "RecordTitle": "6-{[(Tert-butoxy)carbonyl]amino}-2-({[(9H-fluoren-9-YL)methoxy]carbonyl}amino)hexanoic acid",
    "IUPACName": "2-(9H-fluoren-9-ylmethoxycarbonylamino)-6-[(2-methylpropan-2-yl)oxycarbonylamino]hexanoic acid",
    "CASNo": "71989-26-9",
    "MF": "C26H32N2O6",
    "RecordNumber": "100113",
    "MW": "468.5g/mol",
    "Keywords": "CC(C)(C)OC(=O)NCCCCC(C(=O)O)NC(=O)OCC1C2=CC=CC=C2C3=CC=CC=C13",
    "SupplyCount": 26,
    "CID": 100113,
    "titlecn": "N-alpha-芴甲氧羰基-N-epsilon-叔丁氧羰基-L-赖氨酸;"
}