{
    "RecordTitle": "alpha-Carotene",
    "IUPACName": "1,3,3-trimethyl-2-[(1E,3E,5E,7E,9E,11E,13E,15E,17E)-3,7,12,16-tetramethyl-18-[(1R)-2,6,6-trimethylcyclohex-2-en-1-yl]octadeca-1,3,5,7,9,11,13,15,17-nonaenyl]cyclohexene",
    "CASNo": "7488-99-5",
    "MF": "C40H56",
    "RecordNumber": "6419725",
    "MW": "536.9g/mol",
    "Keywords": "CC1=C(C(CCC1)(C)C)/C=C/C(=C/C=C/C(=C/C=C/C=C(\\C)/C=C/C=C(\\C)/C=C/[C@H]2C(=CCCC2(C)C)C)/C)/C",
    "SupplyCount": 11,
    "CID": 6419725,
    "titlecn": "alpha-胡萝卜素;"
}