{
    "RecordTitle": "Montelukast Dicyclohexylamine Salt",
    "IUPACName": "2-[1-[[(1R)-1-[3-[(E)-2-(7-chloroquinolin-2-yl)ethenyl]phenyl]-3-[2-(2-hydroxypropan-2-yl)phenyl]propyl]sulfanylmethyl]cyclopropyl]acetic acid;N-cyclohexylcyclohexanamine",
    "CASNo": "577953-88-9",
    "MF": "C47H59ClN2O3S",
    "RecordNumber": "16202490",
    "MW": "767.5g/mol",
    "Keywords": "CC(C)(C1=CC=CC=C1CC[C@H](C2=CC=CC(=C2)/C=C/C3=NC4=C(C=CC(=C4)Cl)C=C3)SCC5(CC5)CC(=O)O)O.C1CCC(CC1)NC2CCCCC2",
    "SupplyCount": 2,
    "CID": 16202490
}