{
    "RecordTitle": "Pyrethrins",
    "IUPACName": "[(1S)-2-methyl-4-oxo-3-[(2E)-penta-2,4-dienyl]cyclopent-2-en-1-yl] (1R)-2,2-dimethyl-3-(2-methylprop-1-enyl)cyclopropane-1-carboxylate;[2-methyl-4-oxo-3-[(2E)-penta-2,4-dienyl]cyclopent-2-en-1-yl] (1R)-3-[(E)-3-methoxy-2-methyl-3-oxoprop-1-enyl]-2,2-dimethylcyclopropane-1-carboxylate",
    "CASNo": "8003-34-7",
    "MF": "C43H56O8",
    "RecordNumber": "71310221",
    "MW": "700.9g/mol",
    "Keywords": "CC1=C(C(=O)C[C@@H]1OC(=O)[C@@H]2C(C2(C)C)C=C(C)C)C/C=C/C=C.CC1=C(C(=O)CC1OC(=O)[C@@H]2C(C2(C)C)/C=C(\\C)/C(=O)OC)C/C=C/C=C",
    "SupplyCount": 0,
    "CID": 71310221
}