{
    "RecordTitle": "Sildenafil citrate",
    "IUPACName": "5-[2-ethoxy-5-(4-methylpiperazin-1-yl)sulfonylphenyl]-1-methyl-3-propyl-6H-pyrazolo[4,3-d]pyrimidin-7-one;2-hydroxypropane-1,2,3-tricarboxylic acid",
    "CASNo": "171599-83-0",
    "MF": "C28H38N6O11S",
    "RecordNumber": "135413523",
    "MW": "666.703g/mol",
    "Keywords": "CCCC1=NN(C2=C1N=C(NC2=O)C3=C(C=CC(=C3)S(=O)(=O)N4CCN(CC4)C)OCC)C.C(C(=O)O)C(CC(=O)O)(C(=O)O)O",
    "SupplyCount": 30,
    "CID": 135413523,
    "titlecn": "枸橼酸西地那非;1-[4-乙氧基-3-[5-(6,7-二氢-1-甲基-7-氧代-3-丙基-1H-吡唑并[4,3-d]嘧啶)]苯磺酰]-4-甲基;"
}