{
    "RecordTitle": "Polygalacturonase",
    "IUPACName": "(2R)-1-[(4S,7S,10S,13S,16S,19S)-19-amino-7-(2-amino-2-oxoethyl)-10-(3-amino-3-oxopropyl)-13-[(2S)-butan-2-yl]-16-[(4-hydroxyphenyl)methyl]-6,9,12,15,18-pentaoxo-1,2-dithia-5,8,11,14,17-pentazacycloicosane-4-carbonyl]-N-[(2S)-1-[(2-amino-2-oxoethyl)amino]-5-(diaminomethylideneamino)-1-oxopentan-2-yl]pyrrolidine-2-carboxamide",
    "CASNo": "9032-75-1",
    "MF": "C43H67N15O12S2",
    "RecordNumber": "122130350",
    "MW": "1050.222g/mol",
    "Keywords": "CC[C@H](C)[C@H]1C(=O)N[C@H](C(=O)N[C@H](C(=O)N[C@H](CSSC[C@H](C(=O)N[C@H](C(=O)N1)CC2=CC=C(C=C2)O)N)C(=O)N3CCC[C@@H]3C(=O)N[C@@H](CCCN=C(N)N)C(=O)NCC(=O)N)CC(=O)N)CCC(=O)N",
    "SupplyCount": 1,
    "CID": 122130350
}